spark_ddl_parser/__init__.py
spark_ddl_parser/parser.py
spark_ddl_parser/py.typed
spark_ddl_parser/types.py
spark_ddl_parser-0.1.0.dist-info/LICENSE
spark_ddl_parser-0.1.0.dist-info/METADATA
spark_ddl_parser-0.1.0.dist-info/WHEEL
spark_ddl_parser-0.1.0.dist-info/top_level.txt
spark_ddl_parser-0.1.0.dist-info/RECORD
